README.rst
setup.py
src/waldur_azure/__init__.py
src/waldur_azure/admin.py
src/waldur_azure/apps.py
src/waldur_azure/backend.py
src/waldur_azure/cost_tracking.py
src/waldur_azure/driver.py
src/waldur_azure/executors.py
src/waldur_azure/extension.py
src/waldur_azure/filters.py
src/waldur_azure/handlers.py
src/waldur_azure/models.py
src/waldur_azure/serializers.py
src/waldur_azure/urls.py
src/waldur_azure/views.py
src/waldur_azure.egg-info/PKG-INFO
src/waldur_azure.egg-info/SOURCES.txt
src/waldur_azure.egg-info/dependency_links.txt
src/waldur_azure.egg-info/entry_points.txt
src/waldur_azure.egg-info/not-zip-safe
src/waldur_azure.egg-info/requires.txt
src/waldur_azure.egg-info/top_level.txt
src/waldur_azure/migrations/0001_initial.py
src/waldur_azure/migrations/__init__.py
src/waldur_azure/tests/__init__.py
src/waldur_azure/tests/factories.py
src/waldur_azure/tests/fixtures.py
src/waldur_azure/tests/test_driver.py
src/waldur_azure/tests/test_virtual_machines.py
src/waldur_azure/tests/unittests/__init__.py
src/waldur_azure/tests/unittests/test_handlers.py