Metadata-Version: 2.1
Name: waldur-azure
Version: 0.3.5
Summary: Waldur plugin for managing MS Azure resources.
Home-page: https://waldur.com
Author: OpenNode Team
Author-email: info@opennodecloud.com
License: MIT
Platform: UNKNOWN
Classifier: Framework :: Django
Classifier: Intended Audience :: Developers
Classifier: Intended Audience :: System Administrators
Classifier: Operating System :: OS Independent
Classifier: License :: OSI Approved :: MIT License
Provides-Extra: dev
